{
  "openapi": "3.0.1",
  "info": {
    "title": "默认模块",
    "description": "MC服务 API 接口文档",
    "version": "1.0.0"
  },
  "tags": [
    {
      "name": "dashboard"
    },
    {
      "name": "用户问题管理"
    },
    {
      "name": "用户标签管理"
    },
    {
      "name": "租户信息管理"
    },
    {
      "name": "用户信息管理"
    }
  ],
  "paths": {
    "/v1/ai/dashboard/brandReportTotol": {
      "get": {
        "summary": "品牌可见度汇总",
        "deprecated": false,
        "description": "品牌声量和可见度汇总",
        "operationId": "brandReportTotolUsingGET",
        "tags": [
          "dashboard"
        ],
        "parameters": [
          {
            "name": "brandId",
            "in": "query",
            "description": "brandId",
            "required": true,
            "schema": {
              "type": "integer",
              "format": "int64"
            }
          },
          {
            "name": "brandRelevance",
            "in": "query",
            "description": "brandRelevance",
            "required": false,
            "schema": {
              "type": "integer",
              "format": "int32"
            }
          },
          {
            "name": "endTime",
            "in": "query",
            "description": "endTime",
            "required": true,
            "schema": {
              "type": "string"
            }
          },
          {
            "name": "groupNames",
            "in": "query",
            "description": "groupNames",
            "required": false,
            "schema": {
              "type": "array",
              "items": {
                "type": "string"
              }
            }
          },
          {
            "name": "ismonitor",
            "in": "query",
            "description": "ismonitor",
            "required": false,
            "schema": {
              "type": "integer",
              "format": "int32"
            }
          },
          {
            "name": "modelIds",
            "in": "query",
            "description": "modelIds",
            "required": false,
            "schema": {
              "type": "array",
              "items": {
                "type": "integer",
                "format": "int32"
              }
            }
          },
          {
            "name": "startTime",
            "in": "query",
            "description": "startTime",
            "required": true,
            "schema": {
              "type": "string"
            }
          },
          {
            "name": "tagIds",
            "in": "query",
            "description": "tagIds",
            "required": false,
            "schema": {
              "type": "array",
              "items": {
                "type": "integer",
                "format": "int64"
              }
            }
          },
          {
            "name": "tenantId",
            "in": "header",
            "description": "认证TenantId",
            "required": false,
            "example": 0,
            "schema": {
              "type": "integer",
              "format": "int32"
            }
          },
          {
            "name": "token",
            "in": "header",
            "description": "认证Token",
            "required": false,
            "example": "",
            "schema": {
              "type": "string"
            }
          }
        ],
        "responses": {
          "200": {
            "description": "OK",
            "content": {
              "*/*": {
                "schema": {
                  "type": "array",
                  "items": {
                    "$ref": "#/components/schemas/QABrandResultByDayVo"
                  }
                }
              }
            },
            "headers": {}
          },
          "401": {
            "description": "Unauthorized",
            "headers": {}
          },
          "403": {
            "description": "Forbidden",
            "headers": {}
          },
          "404": {
            "description": "Not Found",
            "headers": {}
          }
        },
        "security": []
      }
    },
    "/v1/custQuestion/listGroupName": {
      "post": {
        "summary": "问题分组名列表",
        "deprecated": false,
        "description": "问题分组名列表",
        "operationId": "listGroupNameUsingPOST",
        "tags": [
          "用户问题管理"
        ],
        "parameters": [
          {
            "name": "tenantId",
            "in": "header",
            "description": "认证TenantId",
            "required": false,
            "example": 0,
            "schema": {
              "type": "integer",
              "format": "int32"
            }
          },
          {
            "name": "token",
            "in": "header",
            "description": "认证Token",
            "required": false,
            "example": "",
            "schema": {
              "type": "string"
            }
          }
        ],
        "requestBody": {
          "content": {
            "application/json": {
              "schema": {
                "$ref": "#/components/schemas/GroupNameDto"
              }
            }
          },
          "required": true
        },
        "responses": {
          "200": {
            "description": "OK",
            "content": {
              "*/*": {
                "schema": {
                  "$ref": "#/components/schemas/SingleResult%C2%ABList%C2%ABId2Name%C2%BB%C2%BB"
                }
              }
            },
            "headers": {}
          },
          "201": {
            "description": "Created",
            "headers": {}
          },
          "401": {
            "description": "Unauthorized",
            "headers": {}
          },
          "403": {
            "description": "Forbidden",
            "headers": {}
          },
          "404": {
            "description": "Not Found",
            "headers": {}
          }
        },
        "security": []
      }
    },
    "/v1/custTag/list": {
      "get": {
        "summary": "标签列表",
        "deprecated": false,
        "description": "列表标签",
        "operationId": "listUsingGET_5",
        "tags": [
          "用户标签管理"
        ],
        "parameters": [
          {
            "name": "id",
            "in": "query",
            "description": "id",
            "required": false,
            "schema": {
              "type": "integer",
              "format": "int64"
            }
          },
          {
            "name": "isDimensionTag",
            "in": "query",
            "description": "isDimensionTag",
            "required": false,
            "schema": {
              "type": "boolean",
              "default": false
            }
          },
          {
            "name": "page",
            "in": "query",
            "description": "page",
            "required": false,
            "schema": {
              "type": "integer",
              "format": "int64",
              "default": 1
            }
          },
          {
            "name": "pageSize",
            "in": "query",
            "description": "pageSize",
            "required": false,
            "schema": {
              "type": "integer",
              "format": "int64",
              "default": 10
            }
          },
          {
            "name": "searchKey",
            "in": "query",
            "description": "searchKey",
            "required": false,
            "schema": {
              "type": "string"
            }
          },
          {
            "name": "type",
            "in": "query",
            "description": "type",
            "required": false,
            "schema": {
              "type": "integer",
              "format": "int32",
              "default": 2
            }
          },
          {
            "name": "tenantId",
            "in": "header",
            "description": "认证TenantId",
            "required": false,
            "example": 0,
            "schema": {
              "type": "integer",
              "format": "int32"
            }
          },
          {
            "name": "token",
            "in": "header",
            "description": "认证Token",
            "required": false,
            "example": "",
            "schema": {
              "type": "string"
            }
          }
        ],
        "responses": {
          "200": {
            "description": "OK",
            "content": {
              "*/*": {
                "schema": {
                  "$ref": "#/components/schemas/PageInfo%C2%ABCustTag%C2%BB"
                }
              }
            },
            "headers": {}
          },
          "401": {
            "description": "Unauthorized",
            "headers": {}
          },
          "403": {
            "description": "Forbidden",
            "headers": {}
          },
          "404": {
            "description": "Not Found",
            "headers": {}
          }
        },
        "security": []
      }
    },
    "/v1/tenantInfo/modelList": {
      "get": {
        "summary": "获取租户模型列表",
        "deprecated": false,
        "description": "获取租户模型列表",
        "operationId": "modelListUsingGET",
        "tags": [
          "租户信息管理"
        ],
        "parameters": [
          {
            "name": "tenantId",
            "in": "header",
            "description": "认证TenantId",
            "required": false,
            "example": 0,
            "schema": {
              "type": "integer",
              "format": "int32"
            }
          },
          {
            "name": "token",
            "in": "header",
            "description": "认证Token",
            "required": false,
            "example": "",
            "schema": {
              "type": "string"
            }
          }
        ],
        "responses": {
          "200": {
            "description": "OK",
            "content": {
              "*/*": {
                "schema": {
                  "$ref": "#/components/schemas/SingleResult%C2%ABList%C2%ABCustAIModelVo%C2%BB%C2%BB"
                }
              }
            },
            "headers": {}
          },
          "401": {
            "description": "Unauthorized",
            "headers": {}
          },
          "403": {
            "description": "Forbidden",
            "headers": {}
          },
          "404": {
            "description": "Not Found",
            "headers": {}
          }
        },
        "security": []
      }
    },
    "/v1/user/info": {
      "get": {
        "summary": "用户信息",
        "deprecated": false,
        "description": "",
        "operationId": "infoUsingGET",
        "tags": [
          "用户信息管理"
        ],
        "parameters": [
          {
            "name": "tenantId",
            "in": "header",
            "description": "认证TenantId",
            "required": false,
            "example": 0,
            "schema": {
              "type": "integer",
              "format": "int32"
            }
          },
          {
            "name": "token",
            "in": "header",
            "description": "认证Token",
            "required": false,
            "example": "",
            "schema": {
              "type": "string"
            }
          }
        ],
        "responses": {
          "200": {
            "description": "OK",
            "content": {
              "application/json": {
                "schema": {
                  "$ref": "#/components/schemas/SingleResult%C2%ABRedisSession%C2%BB"
                }
              }
            },
            "headers": {}
          },
          "400": {
            "description": "系统错误",
            "headers": {}
          },
          "401": {
            "description": "Unauthorized",
            "headers": {}
          },
          "403": {
            "description": "Forbidden",
            "headers": {}
          },
          "404": {
            "description": "Not Found",
            "headers": {}
          }
        },
        "security": []
      }
    },
    "/v1/user/login": {
      "post": {
        "summary": "用户登陆",
        "deprecated": false,
        "description": "",
        "operationId": "loginUsingPOST",
        "tags": [
          "用户信息管理"
        ],
        "parameters": [
          {
            "name": "tenantId",
            "in": "header",
            "description": "认证TenantId",
            "required": false,
            "example": 0,
            "schema": {
              "type": "integer",
              "format": "int32"
            }
          },
          {
            "name": "token",
            "in": "header",
            "description": "认证Token",
            "required": false,
            "example": "",
            "schema": {
              "type": "string"
            }
          }
        ],
        "requestBody": {
          "content": {
            "application/json": {
              "schema": {
                "$ref": "#/components/schemas/UserInfoVO"
              }
            }
          }
        },
        "responses": {
          "200": {
            "description": "OK",
            "content": {
              "application/json": {
                "schema": {
                  "$ref": "#/components/schemas/SingleResult%C2%ABRedisSession%C2%BB"
                }
              }
            },
            "headers": {}
          },
          "201": {
            "description": "Created",
            "headers": {}
          },
          "400": {
            "description": "系统错误",
            "headers": {}
          },
          "401": {
            "description": "Unauthorized",
            "headers": {}
          },
          "403": {
            "description": "Forbidden",
            "headers": {}
          },
          "404": {
            "description": "Not Found",
            "headers": {}
          }
        },
        "security": []
      }
    }
  },
  "components": {
    "schemas": {
      "CustAIModelVo": {
        "type": "object",
        "properties": {
          "errorLineCount": {
            "type": "integer",
            "format": "int32",
            "description": "错误行数"
          },
          "id": {
            "type": "integer",
            "format": "int32",
            "description": "主键"
          },
          "isOpen": {
            "type": "integer",
            "format": "int32",
            "description": "是否开通 1是 0否"
          },
          "logo": {
            "type": "string",
            "description": "图标"
          },
          "name": {
            "type": "string",
            "description": "名称"
          },
          "remark": {
            "type": "string",
            "description": "描述"
          }
        },
        "title": "CustAIModelVo"
      },
      "CustTag": {
        "type": "object",
        "properties": {
          "aiName": {
            "type": "string",
            "description": "ai时标签名"
          },
          "ctime": {
            "type": "string",
            "format": "date-time"
          },
          "dimension": {
            "type": "string",
            "description": "维度"
          },
          "historyNum": {
            "type": "integer",
            "format": "int32",
            "description": "问题历史数量"
          },
          "id": {
            "type": "integer",
            "format": "int64",
            "description": "主键"
          },
          "industryId": {
            "type": "integer",
            "format": "int64",
            "description": "行业Id"
          },
          "label": {
            "type": "string",
            "description": "标签的具体类别"
          },
          "level": {
            "type": "integer",
            "format": "int32",
            "description": "层级"
          },
          "monitorNum": {
            "type": "integer",
            "format": "int32",
            "description": "问题监测数量"
          },
          "mtime": {
            "type": "string",
            "format": "date-time"
          },
          "name": {
            "type": "string",
            "description": "标签名 前端展示时"
          },
          "pid": {
            "type": "integer",
            "format": "int64",
            "description": "父Id"
          },
          "sort": {
            "type": "number",
            "description": "排序"
          },
          "status": {
            "type": "integer",
            "format": "int32",
            "description": "状态 1正常 0删除"
          },
          "study": {
            "type": "string",
            "description": "研究对象"
          },
          "tenantId": {
            "type": "integer",
            "format": "int32",
            "description": "租户Id"
          },
          "type": {
            "type": "integer",
            "format": "int32",
            "description": "标签类型 1问题标签 2答案标签"
          },
          "uid": {
            "type": "integer",
            "format": "int64",
            "description": "创建人Id"
          }
        },
        "title": "CustTag"
      },
      "GroupNameDto": {
        "type": "object",
        "properties": {
          "ismonitor": {
            "type": "integer",
            "format": "int32"
          },
          "searchKey": {
            "type": "string"
          },
          "tenantIds": {
            "type": "array",
            "items": {
              "type": "string"
            }
          },
          "tenantStatus": {
            "type": "integer",
            "format": "int32"
          }
        },
        "title": "GroupNameDto"
      },
      "Id2Name": {
        "type": "object",
        "properties": {
          "id": {
            "type": "integer",
            "format": "int64"
          },
          "name": {
            "type": "string"
          },
          "num": {
            "type": "integer",
            "format": "int32"
          },
          "pid": {
            "type": "integer",
            "format": "int64"
          }
        },
        "title": "Id2Name"
      },
      "MemuVo": {
        "type": "object",
        "required": [
          "icon",
          "parentId",
          "parentName",
          "path",
          "sortNo",
          "status",
          "subSystemId",
          "subSystemVo",
          "type"
        ],
        "properties": {
          "ctime": {
            "type": "string",
            "format": "date-time"
          },
          "icon": {
            "type": "string",
            "description": "图标"
          },
          "id": {
            "type": "integer",
            "format": "int32"
          },
          "mtime": {
            "type": "string",
            "format": "date-time"
          },
          "name": {
            "type": "string"
          },
          "note": {
            "type": "string"
          },
          "parentId": {
            "type": "integer",
            "format": "int32",
            "description": "父节点ID"
          },
          "parentName": {
            "type": "string",
            "description": "父节点ID"
          },
          "path": {
            "type": "string",
            "description": "路径"
          },
          "sortNo": {
            "type": "integer",
            "format": "int32",
            "description": "排序号"
          },
          "status": {
            "type": "integer",
            "format": "int32",
            "description": "是否启用 1-是 0-否"
          },
          "subSystemId": {
            "type": "integer",
            "format": "int32",
            "description": "子系统ID"
          },
          "subSystemVo": {
            "$ref": "#/components/schemas/SubSystemVo"
          },
          "type": {
            "type": "integer",
            "format": "int32",
            "description": "类型 1-一级目录 2-二级目录 3-菜单"
          }
        },
        "title": "MemuVo"
      },
      "PageInfo«CustTag»": {
        "type": "object",
        "properties": {
          "code": {
            "type": "integer",
            "format": "int32"
          },
          "data": {
            "type": "array",
            "items": {
              "$ref": "#/components/schemas/CustTag"
            }
          },
          "message": {
            "type": "string"
          },
          "page": {
            "type": "integer",
            "format": "int64"
          },
          "pageSize": {
            "type": "integer",
            "format": "int64"
          },
          "total": {
            "type": "integer",
            "format": "int64"
          },
          "totalPage": {
            "type": "integer",
            "format": "int64"
          }
        },
        "title": "PageInfo«CustTag»"
      },
      "QABrandResultByDayVo": {
        "type": "object",
        "properties": {
          "aiModelId": {
            "type": "integer",
            "format": "int32"
          },
          "askCount": {
            "type": "integer",
            "format": "int32"
          },
          "avgRank": {
            "type": "integer",
            "format": "int32"
          },
          "avgShowCount": {
            "type": "integer",
            "format": "int32"
          },
          "brandId": {
            "type": "integer",
            "format": "int64"
          },
          "brandLogo": {
            "type": "string"
          },
          "brandName": {
            "type": "string"
          },
          "brandType": {
            "type": "integer",
            "format": "int32"
          },
          "brandUrl": {
            "type": "string"
          },
          "cdate": {
            "type": "string"
          },
          "content": {
            "type": "string",
            "description": "问题内容"
          },
          "custAIModelVo": {
            "$ref": "#/components/schemas/CustAIModelVo"
          },
          "custAIModelVos": {
            "type": "array",
            "items": {
              "$ref": "#/components/schemas/CustAIModelVo"
            }
          },
          "day": {
            "type": "string"
          },
          "dimensionCount": {
            "type": "integer",
            "format": "int32"
          },
          "feelCount": {
            "type": "integer",
            "format": "int32"
          },
          "maxRank": {
            "type": "integer",
            "format": "int32"
          },
          "productId": {
            "type": "integer",
            "format": "int64"
          },
          "productName": {
            "type": "string"
          },
          "questionCount": {
            "type": "integer",
            "format": "int32"
          },
          "questionId": {
            "type": "integer",
            "format": "int64",
            "description": "问题Id"
          },
          "rank": {
            "type": "integer",
            "format": "int32"
          },
          "rankCount": {
            "type": "integer",
            "format": "int32"
          },
          "rankRate": {
            "type": "number",
            "format": "float"
          },
          "rankTop1": {
            "type": "integer",
            "format": "int32"
          },
          "rankTop10": {
            "type": "integer",
            "format": "int32"
          },
          "rankTop10Rate": {
            "type": "number",
            "format": "float"
          },
          "rankTop1Rate": {
            "type": "number",
            "format": "float"
          },
          "rankTop3": {
            "type": "integer",
            "format": "int32"
          },
          "rankTop3Rate": {
            "type": "number",
            "format": "float"
          },
          "refNum": {
            "type": "integer",
            "format": "int32"
          },
          "refRate": {
            "type": "number",
            "format": "float"
          },
          "showCount": {
            "type": "integer",
            "format": "int32"
          },
          "showRate": {
            "type": "number",
            "format": "float"
          },
          "showTGIRate": {
            "type": "number",
            "format": "float"
          },
          "totalShowCount": {
            "type": "integer",
            "format": "int32"
          },
          "zmRate": {
            "type": "number",
            "format": "float"
          },
          "zmRefRate": {
            "type": "number",
            "format": "float"
          }
        },
        "title": "QABrandResultByDayVo",
        "description": "分日声量"
      },
      "RedisSession": {
        "type": "object",
        "properties": {
          "attributes": {
            "type": "object",
            "properties": {}
          },
          "subSystemVos": {
            "type": "array",
            "items": {
              "$ref": "#/components/schemas/SubSystemVo"
            }
          },
          "token": {
            "type": "string"
          },
          "url": {
            "type": "string"
          }
        },
        "title": "RedisSession"
      },
      "SingleResult«List«CustAIModelVo»»": {
        "type": "object",
        "properties": {
          "code": {
            "type": "integer",
            "format": "int32"
          },
          "data": {
            "type": "array",
            "items": {
              "$ref": "#/components/schemas/CustAIModelVo"
            }
          },
          "message": {
            "type": "string"
          }
        },
        "title": "SingleResult«List«CustAIModelVo»»"
      },
      "SingleResult«List«Id2Name»»": {
        "type": "object",
        "properties": {
          "code": {
            "type": "integer",
            "format": "int32"
          },
          "data": {
            "type": "array",
            "items": {
              "$ref": "#/components/schemas/Id2Name"
            }
          },
          "message": {
            "type": "string"
          }
        },
        "title": "SingleResult«List«Id2Name»»"
      },
      "SingleResult«RedisSession»": {
        "type": "object",
        "properties": {
          "code": {
            "type": "integer",
            "format": "int32"
          },
          "data": {
            "$ref": "#/components/schemas/RedisSession"
          },
          "message": {
            "type": "string"
          }
        },
        "title": "SingleResult«RedisSession»"
      },
      "SubSystemVo": {
        "type": "object",
        "required": [
          "home_page",
          "sortNo"
        ],
        "properties": {
          "home_page": {
            "type": "string",
            "description": "首页地址"
          },
          "id": {
            "type": "integer",
            "format": "int32"
          },
          "memuVos": {
            "type": "array",
            "items": {
              "$ref": "#/components/schemas/MemuVo"
            }
          },
          "name": {
            "type": "string"
          },
          "note": {
            "type": "string"
          },
          "sortNo": {
            "type": "integer",
            "format": "int32",
            "description": "排序号"
          }
        },
        "title": "SubSystemVo"
      },
      "UserInfoVO": {
        "type": "object",
        "required": [
          "ctime",
          "id",
          "mobileNum",
          "mtime",
          "passWord",
          "tenantId",
          "userName"
        ],
        "properties": {
          "ctime": {
            "type": "string",
            "format": "date-time",
            "description": "创建时间"
          },
          "id": {
            "type": "integer",
            "format": "int64",
            "description": "id"
          },
          "level": {
            "type": "integer",
            "format": "int32",
            "description": "账号等级 0账号管家 1主账号 2子账号"
          },
          "mobileNum": {
            "type": "string",
            "description": "手机号"
          },
          "mtime": {
            "type": "string",
            "format": "date-time",
            "description": "修改时间"
          },
          "passWord": {
            "type": "string",
            "description": "密码"
          },
          "qywxUserId": {
            "type": "string",
            "description": "企业微信userId"
          },
          "remark": {
            "type": "string",
            "description": "备注"
          },
          "tenantId": {
            "type": "integer",
            "format": "int32",
            "description": "租户id"
          },
          "userName": {
            "type": "string",
            "description": "账户名"
          }
        },
        "title": "UserInfoVO",
        "description": "用户信息"
      }
    },
    "responses": {},
    "securitySchemes": {}
  },
  "servers": [],
  "security": []
}